setup.py
src/google_sheet_tables/__init__.py
src/google_sheet_tables/client.py
src/google_sheet_tables/format.py
src/google_sheet_tables.egg-info/PKG-INFO
src/google_sheet_tables.egg-info/SOURCES.txt
src/google_sheet_tables.egg-info/dependency_links.txt
src/google_sheet_tables.egg-info/requires.txt
src/google_sheet_tables.egg-info/top_level.txt