Metadata-Version: 2.1
Name: google-sheet-tables
Version: 0.0.dev4
Summary: Библиотека для работы с гугл таблицами.
